odoo/addons/sale_cutoff_time_delivery/README.rst
odoo/addons/sale_cutoff_time_delivery/__init__.py
odoo/addons/sale_cutoff_time_delivery/__manifest__.py
odoo/addons/sale_cutoff_time_delivery/i18n/ca.po
odoo/addons/sale_cutoff_time_delivery/i18n/de.po
odoo/addons/sale_cutoff_time_delivery/i18n/es.po
odoo/addons/sale_cutoff_time_delivery/i18n/fr.po
odoo/addons/sale_cutoff_time_delivery/i18n/fr_CH.po
odoo/addons/sale_cutoff_time_delivery/i18n/it.po
odoo/addons/sale_cutoff_time_delivery/i18n/sale_cutoff_time_delivery.pot
odoo/addons/sale_cutoff_time_delivery/models/__init__.py
odoo/addons/sale_cutoff_time_delivery/models/cutoff_time_mixin.py
odoo/addons/sale_cutoff_time_delivery/models/res_partner.py
odoo/addons/sale_cutoff_time_delivery/models/sale_order.py
odoo/addons/sale_cutoff_time_delivery/models/stock_picking.py
odoo/addons/sale_cutoff_time_delivery/models/stock_warehouse.py
odoo/addons/sale_cutoff_time_delivery/readme/CONFIGURE.rst
odoo/addons/sale_cutoff_time_delivery/readme/CONTRIBUTORS.rst
odoo/addons/sale_cutoff_time_delivery/readme/DESCRIPTION.rst
odoo/addons/sale_cutoff_time_delivery/readme/ROADMAP.rst
odoo/addons/sale_cutoff_time_delivery/reports/sale_order.xml
odoo/addons/sale_cutoff_time_delivery/reports/stock_picking.xml
odoo/addons/sale_cutoff_time_delivery/static/description/icon.png
odoo/addons/sale_cutoff_time_delivery/static/description/index.html
odoo/addons/sale_cutoff_time_delivery/tests/__init__.py
odoo/addons/sale_cutoff_time_delivery/tests/test_sale_cutoff_time_delivery.py
odoo/addons/sale_cutoff_time_delivery/views/res_partner.xml
odoo/addons/sale_cutoff_time_delivery/views/stock_picking_views.xml
odoo/addons/sale_cutoff_time_delivery/views/stock_warehouse.xml
odoo13_addon_sale_cutoff_time_delivery-13.0.1.4.1.dist-info/METADATA
odoo13_addon_sale_cutoff_time_delivery-13.0.1.4.1.dist-info/WHEEL
odoo13_addon_sale_cutoff_time_delivery-13.0.1.4.1.dist-info/top_level.txt
odoo13_addon_sale_cutoff_time_delivery-13.0.1.4.1.dist-info/RECORD
